ibis_singlestoredb/__init__.py
ibis_singlestoredb/compiler.py
ibis_singlestoredb/datatypes.py
ibis_singlestoredb/expr.py
ibis_singlestoredb/registry.py
ibis_singlestoredb/sqlglot.py
ibis_singlestoredb/functions/__init__.py
ibis_singlestoredb/functions/general.py
ibis_singlestoredb/functions/user.py
ibis_singlestoredb/functions/json/__init__.py
ibis_singlestoredb/functions/json/json_agg.py
ibis_singlestoredb/functions/json/json_array_contains.py
ibis_singlestoredb/functions/json/json_array_push.py
ibis_singlestoredb/functions/json/json_delete_key.py
ibis_singlestoredb/functions/json/json_extract.py
ibis_singlestoredb/functions/json/json_get_type.py
ibis_singlestoredb/functions/json/json_include_exclude_mask.py
ibis_singlestoredb/functions/json/json_keys.py
ibis_singlestoredb/functions/json/json_length.py
ibis_singlestoredb/functions/json/json_match_any.py
ibis_singlestoredb/functions/json/json_pretty.py
ibis_singlestoredb/functions/json/json_set.py
ibis_singlestoredb/functions/json/json_splice.py
ibis_singlestoredb/functions/json/json_to_array.py
ibis_singlestoredb/functions/json/to_json.py
ibis_singlestoredb/functions/numeric/__init__.py
ibis_singlestoredb/functions/vector/__init__.py
ibis_singlestoredb/functions/vector/dot_product.py
ibis_singlestoredb/functions/vector/euclidean_distance.py
ibis_singlestoredb/functions/vector/json_array_pack.py
ibis_singlestoredb/functions/vector/json_array_unpack.py
ibis_singlestoredb/functions/vector/scalar_vector_mul.py
ibis_singlestoredb/functions/vector/vector_add.py
ibis_singlestoredb/functions/vector/vector_elements_sum.py
ibis_singlestoredb/functions/vector/vector_kth_element.py
ibis_singlestoredb/functions/vector/vector_mul.py
ibis_singlestoredb/functions/vector/vector_num_elements.py
ibis_singlestoredb/functions/vector/vector_sort.py
ibis_singlestoredb/functions/vector/vector_sub.py
ibis_singlestoredb/functions/vector/vector_subvector.py
ibis_singlestoredb/functions/vector/vector_sum.py
ibis_singlestoredb-0.4.2.dist-info/LICENSE
ibis_singlestoredb-0.4.2.dist-info/METADATA
ibis_singlestoredb-0.4.2.dist-info/WHEEL
ibis_singlestoredb-0.4.2.dist-info/entry_points.txt
ibis_singlestoredb-0.4.2.dist-info/top_level.txt
ibis_singlestoredb-0.4.2.dist-info/RECORD
