Metadata-Version: 2.1
Name: ibis-singlestoredb
Version: 0.4.2
Summary: Ibis backend for the SingleStoreDB database
Home-page: https://github.com/singlestore-labs/ibis-singlestoredb
Author: SingleStore
Author-email: support@singlestore.com
License: Apache-2.0
Classifier: Development Status :: 4 - Beta
Classifier: License :: OSI Approved :: Apache Software License
Classifier: Programming Language :: Python :: 3
Classifier: Programming Language :: Python :: 3 :: Only
Classifier: Programming Language :: Python :: 3.8
Classifier: Programming Language :: Python :: 3.9
Classifier: Programming Language :: Python :: 3.10
Classifier: Topic :: Database
Classifier: Topic :: Scientific/Engineering
Requires-Python: >=3.8
License-File: LICENSE
Requires-Dist: ibis-framework <7.0.0dev,>=6.1.0
Requires-Dist: singlestoredb >=0.8.6
Requires-Dist: sqlalchemy-singlestoredb >=0.3.1
